_mgp.py
mgp.py
mgp-1.1.1.dist-info/LICENSE
mgp-1.1.1.dist-info/WHEEL
mgp-1.1.1.dist-info/METADATA
mgp-1.1.1.dist-info/RECORD
