Metadata-Version: 2.1
Name: mgp
Version: 1.1.1
Summary: Memgraph's module for developing MAGE modules. Used only for type hinting!
License: Apache-2.0
Author: katarinasupe
Author-email: katarina.supe@memgraph.io
Requires-Python: >=3.7,<4.0
Classifier: License :: OSI Approved :: Apache Software License
Classifier: Programming Language :: Python :: 3
Classifier: Programming Language :: Python :: 3.7
Classifier: Programming Language :: Python :: 3.8
Classifier: Programming Language :: Python :: 3.9
Classifier: Programming Language :: Python :: 3.10
